{"OPIM 101":{"courseListName":"OPIM 101","courseTitle":"An Introduction to Operations and Information Management","PCR":2.72},"OPIM 105":{"courseListName":"OPIM 105","courseTitle":"Developing Tools for Data Access and Analysis (VBA and SQL Programming)","PCR":3.56},"OPIM 240":{"courseListName":"OPIM 240","courseTitle":"Gamification for Business","PCR":2.96},"OPIM 290":{"courseListName":"OPIM 290","courseTitle":"Decision Processes","PCR":3.47},"OPIM 291":{"courseListName":"OPIM 291","courseTitle":"Negotiations","PCR":3.02},"OPIM 299":{"courseListName":"OPIM 299","courseTitle":"Judg & Dec Making Res Im"},"OPIM 314":{"courseListName":"OPIM 314","courseTitle":"Enabling Technologies","PCR":3.23},"OPIM 321":{"courseListName":"OPIM 321","courseTitle":"Introduction to Management Science","PCR":3.23},"OPIM 415":{"courseListName":"OPIM 415","courseTitle":"Product Design","PCR":3.07},"OPIM 611":{"courseListName":"OPIM 611","courseTitle":"Quality and Productivity"},"OPIM 614":{"courseListName":"OPIM 614","courseTitle":"Innovation","PCR":2.86},"OPIM 615":{"courseListName":"OPIM 615","courseTitle":"Operations Strategy","PCR":2.58},"OPIM 652":{"courseListName":"OPIM 652","courseTitle":"Advanced Management Science: Models and Applications","PCR":3.62},"OPIM 659":{"courseListName":"OPIM 659","courseTitle":"Advanced Topics in Quantitative Methods and Operations Management","PCR":3.08},"OPIM 662":{"courseListName":"OPIM 662","courseTitle":"Enabling Technologies","PCR":3.19},"OPIM 673":{"courseListName":"OPIM 673","courseTitle":"Global Supply Chain Mgmt.","PCR":2.63},"OPIM 690":{"courseListName":"OPIM 690","courseTitle":"Managerial Decision Making","PCR":3.23},"OPIM 691":{"courseListName":"OPIM 691","courseTitle":"Negotiations","PCR":2.85},"OPIM 699":{"courseListName":"OPIM 699","courseTitle":"Advanced Topics","PCR":2.43},"OPIM 910":{"courseListName":"OPIM 910","courseTitle":"Concepts of Math Programming","PCR":2.34},"OPIM 912":{"courseListName":"OPIM 912","courseTitle":"Optimization","PCR":3.23},"OPIM 930":{"courseListName":"OPIM 930","courseTitle":"Stochastic Models","PCR":3.18},"OPIM 940":{"courseListName":"OPIM 940","courseTitle":"Operations Management"}}