{"ARTH 100":[{"InstID":"6834-LISA-ARIES-HOMANN","revID":"32554","Rating":"2.25"},{"InstID":"1410-AARON-LEVY","revID":"32554","Rating":"3.44"}],"ARTH 101":[{"InstID":"3894-ROBERT-G--OUSTERHOUT","revID":"31233","Rating":"2.80"},{"InstID":"6622-ARIEL-L-PEARCE","revID":"31233","Rating":"3.43"}],"ARTH 102":[{"InstID":"4746-ANDRE-DOMBROWSKI","revID":"32555","Rating":"2.89"},{"InstID":"2862-GWENDOLYN-D-SHAW","revID":"32555","Rating":"2.89"},{"InstID":"6835-MIYA-TOKUMITSU","revID":"32555","Rating":"2.83"}],"ARTH 106":[{"InstID":"127-LOTHAR-HASELBERGER","revID":"31235","Rating":"3.26"}],"ARTH 221":[{"InstID":"1265-ANN-L--KUTTNER","revID":"25628","Rating":"1.42"},{"InstID":"1265-ANN-L--KUTTNER","revID":"25628","Rating":"1.42"}],"ARTH 222":[{"InstID":"140-HOLLY-PITTMAN","revID":"32556","Rating":"2.87"},{"InstID":"140-HOLLY-PITTMAN","revID":"32556","Rating":"2.87"}],"ARTH 240":[{"InstID":"124-ROBERT-A--MAXWELL","revID":"29877","Rating":"3.00"},{"InstID":"124-ROBERT-A--MAXWELL","revID":"29877","Rating":"3.00"}],"ARTH 282":[{"InstID":"1271-DAVID-B-BROWNLEE","revID":"28562","Rating":"3.44"},{"InstID":"1271-DAVID-B-BROWNLEE","revID":"28562","Rating":"3.44"}],"ARTH 284":[{"InstID":"4746-ANDRE-DOMBROWSKI","revID":"24008","Rating":"3.70"},{"InstID":"4746-ANDRE-DOMBROWSKI","revID":"24008","Rating":"3.70"}],"ARTH 287":[{"InstID":"5288-KAJA-SILVERMAN","revID":"29882","Rating":"3.69"},{"InstID":"5288-KAJA-SILVERMAN","revID":"29882","Rating":"3.69"}],"ARTH 289":[{"InstID":"2857-MICHAEL-LEJA","revID":"11442","Rating":"3.64"}],"ARTH 689":[{"InstID":"134-REBECCA-BUTTERFIELD","revID":"163","Rating":"3.39"},{"InstID":"134-REBECCA-BUTTERFIELD","revID":"163","Rating":"3.39"}],"ARTH 301":[{"InstID":"6635-TERRI-S--FRANCIS","revID":"32716","Rating":"3.33"}],"ARTH 408":[{"InstID":"138-MOLLIE-MCNICKLE","revID":"165","Rating":"3.00"}],"ARTH 475":[{"InstID":"139-JON-SEYDL","revID":"166","Rating":"3.33"}],"ARTH 523":[{"InstID":"141-ALEKSANDR-LESKOV","revID":"168","Rating":"2.00"}],"ARTH 552":[{"InstID":"1268-CHRISTOPHER-PASTORE","revID":"24017","Rating":"3.00"}],"ARTH 433":[{"InstID":"74-S--NOMANUL-HAQ","revID":"85","Rating":"1.83"}],"ARTH 132":[{"InstID":"257-ALEXANDER-A-BAUER","revID":"274","Rating":"3.71"}],"ARTH 225":[{"InstID":"127-LOTHAR-HASELBERGER","revID":"29876","Rating":"2.77"},{"InstID":"127-LOTHAR-HASELBERGER","revID":"29876","Rating":"2.77"}],"ARTH 009":[{"InstID":"5558-GEOFFREY-E-SHAMOS","revID":"22551","Rating":"2.25"},{"InstID":"5000-ALISON-W-CHANG","revID":"22551","Rating":"2.60"},{"InstID":"5000-ALISON-W-CHANG","revID":"22551","Rating":"3.00"},{"InstID":"4626-ISABEL-J-SUCHANEK","revID":"22551","Rating":"3.14"},{"InstID":"124-ROBERT-A--MAXWELL","revID":"22551","Rating":"0.75"},{"InstID":"4626-ISABEL-J-SUCHANEK","revID":"22551","Rating":"3.25"}],"ARTH 211":[{"InstID":"1789-DEBORAH-E-KLIMBURG-SALTER","revID":"1321","Rating":"1.57"}],"ARTH 251":[{"InstID":"3528-MAIA-GAHTAN","revID":"20969","Rating":"3.75"},{"InstID":"3528-MAIA-GAHTAN","revID":"20969","Rating":"3.40"}],"ARTH 288":[{"InstID":"1273-GEORGE-H--MARCUS","revID":"32562","Rating":"2.77"}],"ARTH 422":[{"InstID":"140-HOLLY-PITTMAN","revID":"14115","Rating":"3.38"}],"ARTH 512":[{"InstID":"144-MICHAEL-W-MEISTER","revID":"1331","Rating":"3.14"}],"ARTH 521":[{"InstID":"1265-ANN-L--KUTTNER","revID":"28568","Rating":"2.42"}],"ARTH 528":[{"InstID":"127-LOTHAR-HASELBERGER","revID":"29891","Rating":"3.75"}],"ARTH 588":[{"InstID":"6231-KATHLEEN-ADAIR-FOSTER","revID":"28570","Rating":"3.10"},{"InstID":"2857-MICHAEL-LEJA","revID":"28570","Rating":"3.10"}],"ARTH 104":[{"InstID":"144-MICHAEL-W-MEISTER","revID":"31234","Rating":"1.78"}],"ARTH 213":[{"InstID":"1267-JULIE-NELSON-DAVIS","revID":"28559","Rating":"3.50"},{"InstID":"1267-JULIE-NELSON-DAVIS","revID":"28559","Rating":"3.50"}],"ARTH 220":[{"InstID":"1265-ANN-L--KUTTNER","revID":"28560","Rating":"2.43"},{"InstID":"1265-ANN-L--KUTTNER","revID":"28560","Rating":"2.43"}],"ARTH 242":[{"InstID":"124-ROBERT-A--MAXWELL","revID":"19785","Rating":"3.20"}],"ARTH 252":[{"InstID":"1268-CHRISTOPHER-PASTORE","revID":"29878","Rating":"3.67"},{"InstID":"1268-CHRISTOPHER-PASTORE","revID":"29878","Rating":"3.67"}],"ARTH 271":[{"InstID":"1982-LARRY-A--SILVER","revID":"24007","Rating":"3.26"},{"InstID":"1982-LARRY-A--SILVER","revID":"24007","Rating":"3.26"}],"ARTH 280":[{"InstID":"1270-NATASHA-RUIZ-GOMEZ","revID":"2642","Rating":"3.00"}],"ARTH 281":[{"InstID":"6042-CAROL-A-HAGAN","revID":"32561","Rating":"3.11"},{"InstID":"6042-CAROL-A-HAGAN","revID":"32561","Rating":"3.11"}],"ARTH 285":[{"InstID":"4746-ANDRE-DOMBROWSKI","revID":"22662","Rating":"3.47"},{"InstID":"4746-ANDRE-DOMBROWSKI","revID":"22662","Rating":"3.47"}],"ARTH 286":[{"InstID":"126-CHRISTINE-POGGI","revID":"31242","Rating":"3.29"},{"InstID":"126-CHRISTINE-POGGI","revID":"31242","Rating":"3.29"}],"ARTH 293":[{"InstID":"134-REBECCA-BUTTERFIELD","revID":"25634","Rating":"3.16"}],"ARTH 295":[{"InstID":"2862-GWENDOLYN-D-SHAW","revID":"14113","Rating":"3.33"}],"ARTH 417":[{"InstID":"128-RENATA-HOLOD","revID":"26989","Rating":"3.14"}],"ARTH 492":[{"InstID":"134-REBECCA-BUTTERFIELD","revID":"2650","Rating":"3.90"}],"ARTH 513":[{"InstID":"1982-LARRY-A--SILVER","revID":"29889","Rating":"3.33"},{"InstID":"1267-JULIE-NELSON-DAVIS","revID":"29889","Rating":"3.33"}],"ARTH 579":[{"InstID":"1269-ZIRKA-FILIPCZAK","revID":"2652","Rating":"2.80"}],"ARTH 001":[{"InstID":"127-LOTHAR-HASELBERGER","revID":"18290","Rating":"3.22"}],"ARTH 212":[{"InstID":"144-MICHAEL-W-MEISTER","revID":"28558","Rating":"1.60"},{"InstID":"144-MICHAEL-W-MEISTER","revID":"28558","Rating":"1.60"}],"ARTH 218":[{"InstID":"1267-JULIE-NELSON-DAVIS","revID":"29875","Rating":"3.67"},{"InstID":"1267-JULIE-NELSON-DAVIS","revID":"29875","Rating":"3.67"}],"ARTH 223":[{"InstID":"3219-BETH-JUDAS","revID":"18295","Rating":"2.50"}],"ARTH 241":[{"InstID":"3894-ROBERT-G--OUSTERHOUT","revID":"25630","Rating":"3.00"},{"InstID":"3894-ROBERT-G--OUSTERHOUT","revID":"25630","Rating":"3.00"}],"ARTH 255":[{"InstID":"5710-CHRISTOPHER-J-NYGREN","revID":"24006","Rating":"3.73"},{"InstID":"5710-CHRISTOPHER-J-NYGREN","revID":"24006","Rating":"3.73"}],"ARTH 262":[{"InstID":"1982-LARRY-A--SILVER","revID":"3792","Rating":"3.59"}],"ARTH 283":[{"InstID":"1271-DAVID-B-BROWNLEE","revID":"22661","Rating":"3.38"},{"InstID":"1271-DAVID-B-BROWNLEE","revID":"22661","Rating":"3.38"}],"ARTH 290":[{"InstID":"1267-JULIE-NELSON-DAVIS","revID":"32563","Rating":"3.41"},{"InstID":"1267-JULIE-NELSON-DAVIS","revID":"32563","Rating":"3.41"}],"ARTH 527":[{"InstID":"127-LOTHAR-HASELBERGER","revID":"3802","Rating":"2.50"}],"ARTH 586":[{"InstID":"134-REBECCA-BUTTERFIELD","revID":"31251","Rating":"2.82"}],"ARTH 354":[{"InstID":"2033-PAMELA-BLAKELY","revID":"19717","Rating":"3.13"}],"ARTH 103":[{"InstID":"1237-NANCY-R--S--STEINHARDT","revID":"31466","Rating":"2.29"}],"ARTH 224":[{"InstID":"140-HOLLY-PITTMAN","revID":"28561","Rating":"1.86"},{"InstID":"140-HOLLY-PITTMAN","revID":"28561","Rating":"1.86"}],"ARTH 253":[{"InstID":"2059-MICHAEL-W-COLE","revID":"4992","Rating":"3.04"},{"InstID":"2059-MICHAEL-W-COLE","revID":"4992","Rating":"3.04"}],"ARTH 653":[{"InstID":"2059-MICHAEL-W-COLE","revID":"4992","Rating":"3.04"},{"InstID":"2059-MICHAEL-W-COLE","revID":"4992","Rating":"3.04"}],"ARTH 260":[{"InstID":"1982-LARRY-A--SILVER","revID":"4993","Rating":"3.73"}],"ARTH 420":[{"InstID":"1265-ANN-L--KUTTNER","revID":"7348","Rating":"2.67"}],"ARTH 518":[{"InstID":"128-RENATA-HOLOD","revID":"26992","Rating":"3.86"},{"InstID":"6043-YAEL-R-RICE","revID":"26992","Rating":"3.86"}],"ARTH 562":[{"InstID":"1982-LARRY-A--SILVER","revID":"22672","Rating":"3.50"}],"ARTH 593":[{"InstID":"4748-PATRICIA-A-WHITE","revID":"31252","Rating":"3.43"}],"ARTH 214":[{"InstID":"1237-NANCY-R--S--STEINHARDT","revID":"22895","Rating":"2.76"},{"InstID":"1237-NANCY-R--S--STEINHARDT","revID":"22895","Rating":"2.76"}],"ARTH 291":[{"InstID":"2407-KAREN-BECKMAN","revID":"18302","Rating":"3.30"}],"ARTH 292":[{"InstID":"3224-META-MAZAJ","revID":"28702","Rating":"3.45"}],"ARTH 002":[{"InstID":"126-CHRISTINE-POGGI","revID":"25621","Rating":"2.82"},{"InstID":"4746-ANDRE-DOMBROWSKI","revID":"25621","Rating":"2.82"}],"ARTH 201":[{"InstID":"2861-EVELYN-M-COHEN","revID":"7334","Rating":"2.50"}],"ARTH 217":[{"InstID":"6230-JULIA-A-PERRATORE","revID":"29874","Rating":"2.00"},{"InstID":"6230-JULIA-A-PERRATORE","revID":"29874","Rating":"2.00"}],"ARTH 219":[{"InstID":"74-S--NOMANUL-HAQ","revID":"6182","Rating":"2.80"}],"ARTH 227":[{"InstID":"127-LOTHAR-HASELBERGER","revID":"7339","Rating":"3.75"}],"ARTH 229":[{"InstID":"127-LOTHAR-HASELBERGER","revID":"32557","Rating":"3.50"},{"InstID":"127-LOTHAR-HASELBERGER","revID":"32557","Rating":"3.50"}],"ARTH 275":[{"InstID":"1790-SUZANNE-GLOVER-LINDSAY","revID":"29881","Rating":"2.59"},{"InstID":"1790-SUZANNE-GLOVER-LINDSAY","revID":"29881","Rating":"2.59"}],"ARTH 276":[{"InstID":"143-VICTORIA-GARDNER-COATES","revID":"6188","Rating":"3.00"}],"ARTH 411":[{"InstID":"74-S--NOMANUL-HAQ","revID":"6193","Rating":"2.83"}],"ARTH 414":[{"InstID":"1267-JULIE-NELSON-DAVIS","revID":"6194","Rating":"2.88"}],"ARTH 525":[{"InstID":"130-ELIZABETH-SHANK","revID":"25639","Rating":"3.75"}],"ARTH 202":[{"InstID":"3210-THOMAS-F--TARTARON","revID":"15523","Rating":"3.00"}],"ARTH 210":[{"InstID":"1267-JULIE-NELSON-DAVIS","revID":"16970","Rating":"3.40"},{"InstID":"1267-JULIE-NELSON-DAVIS","revID":"16970","Rating":"3.40"}],"ARTH 424":[{"InstID":"137-ANN-BLAIR-BROWNLEE","revID":"10071","Rating":"2.77"}],"ARTH 587":[{"InstID":"3897-AMY-ELISABETH-FREUND","revID":"12901","Rating":"3.50"}],"ARTH 589":[{"InstID":"1273-GEORGE-H--MARCUS","revID":"25640","Rating":"2.71"}],"ARTH 228":[{"InstID":"2898-CHARLES-BRIAN-ROSE","revID":"7491","Rating":"3.78"}],"ARTH 526":[{"InstID":"2898-CHARLES-BRIAN-ROSE","revID":"31437","Rating":"3.80"}],"ARTH 108":[{"InstID":"3224-META-MAZAJ","revID":"32708","Rating":"3.40"}],"ARTH 473":[{"InstID":"654-EDWARD-M-PETERS","revID":"7886","Rating":"2.25"},{"InstID":"1982-LARRY-A--SILVER","revID":"7886","Rating":"2.36"}],"ARTH 105":[{"InstID":"5969-KAREN-SONIK","revID":"25625","Rating":"2.32"}],"ARTH 412":[{"InstID":"144-MICHAEL-W-MEISTER","revID":"8548","Rating":"2.00"}],"ARTH 501":[{"InstID":"639-ROBERT-B--ST-GEORGE","revID":"31247","Rating":"2.44"},{"InstID":"1982-LARRY-A--SILVER","revID":"31247","Rating":"2.44"}],"ARTH 585":[{"InstID":"4746-ANDRE-DOMBROWSKI","revID":"21301","Rating":"3.57"}],"ARTH 118":[{"InstID":"3219-BETH-JUDAS","revID":"31236","Rating":"2.50"}],"ARTH 216":[{"InstID":"1237-NANCY-R--S--STEINHARDT","revID":"24245","Rating":"3.13"}],"ARTH 109":[{"InstID":"2124-TIMOTHY-CORRIGAN","revID":"32859","Rating":"3.32"}],"ARTH 541":[{"InstID":"1048-E-ANN-MATTER","revID":"26995","Rating":"2.40"},{"InstID":"124-ROBERT-A--MAXWELL","revID":"26995","Rating":"2.40"}],"ARTH 215":[{"InstID":"1267-JULIE-NELSON-DAVIS","revID":"11433","Rating":"3.08"}],"ARTH 209":[{"InstID":"2033-PAMELA-BLAKELY","revID":"28488","Rating":"2.55"}],"ARTH 296":[{"InstID":"134-REBECCA-BUTTERFIELD","revID":"22664","Rating":"2.82"}],"ARTH 614":[{"InstID":"1237-NANCY-R--S--STEINHARDT","revID":"22895","Rating":"2.76"},{"InstID":"1237-NANCY-R--S--STEINHARDT","revID":"22895","Rating":"2.76"}],"ARTH 584":[{"InstID":"1480-CATRIONA-MACLEOD","revID":"13352","Rating":"4.00"}],"ARTH 107":[{"InstID":"3224-META-MAZAJ","revID":"32709","Rating":"2.92"}],"ARTH 618":[{"InstID":"1267-JULIE-NELSON-DAVIS","revID":"29875","Rating":"3.67"},{"InstID":"1267-JULIE-NELSON-DAVIS","revID":"29875","Rating":"3.67"}],"ARTH 621":[{"InstID":"1265-ANN-L--KUTTNER","revID":"25628","Rating":"1.42"},{"InstID":"1265-ANN-L--KUTTNER","revID":"25628","Rating":"1.42"}],"ARTH 625":[{"InstID":"127-LOTHAR-HASELBERGER","revID":"29876","Rating":"2.77"},{"InstID":"127-LOTHAR-HASELBERGER","revID":"29876","Rating":"2.77"}],"ARTH 641":[{"InstID":"3894-ROBERT-G--OUSTERHOUT","revID":"25630","Rating":"3.00"},{"InstID":"3894-ROBERT-G--OUSTERHOUT","revID":"25630","Rating":"3.00"}],"ARTH 642":[{"InstID":"124-ROBERT-A--MAXWELL","revID":"15352","Rating":"2.45"},{"InstID":"124-ROBERT-A--MAXWELL","revID":"15352","Rating":"2.45"}],"ARTH 671":[{"InstID":"1982-LARRY-A--SILVER","revID":"24007","Rating":"3.26"},{"InstID":"1982-LARRY-A--SILVER","revID":"24007","Rating":"3.26"}],"ARTH 682":[{"InstID":"1271-DAVID-B-BROWNLEE","revID":"28562","Rating":"3.44"},{"InstID":"1271-DAVID-B-BROWNLEE","revID":"28562","Rating":"3.44"}],"ARTH 687":[{"InstID":"5288-KAJA-SILVERMAN","revID":"29882","Rating":"3.69"},{"InstID":"5288-KAJA-SILVERMAN","revID":"29882","Rating":"3.69"}],"ARTH 696":[{"InstID":"134-REBECCA-BUTTERFIELD","revID":"15357","Rating":"3.14"},{"InstID":"134-REBECCA-BUTTERFIELD","revID":"15357","Rating":"3.14"}],"ARTH 599":[{"InstID":"144-MICHAEL-W-MEISTER","revID":"15366","Rating":"3.25"}],"ARTH 170":[{"InstID":"5976-SUSAN-J-NAPIER","revID":"25784","Rating":"2.38"}],"ARTH 320":[{"InstID":"5976-SUSAN-J-NAPIER","revID":"25790","Rating":"2.80"}],"ARTH 610":[{"InstID":"1267-JULIE-NELSON-DAVIS","revID":"16970","Rating":"3.40"},{"InstID":"1267-JULIE-NELSON-DAVIS","revID":"16970","Rating":"3.40"}],"ARTH 617":[{"InstID":"6230-JULIA-A-PERRATORE","revID":"29874","Rating":"2.00"},{"InstID":"6230-JULIA-A-PERRATORE","revID":"29874","Rating":"2.00"}],"ARTH 620":[{"InstID":"1265-ANN-L--KUTTNER","revID":"28560","Rating":"2.43"},{"InstID":"1265-ANN-L--KUTTNER","revID":"28560","Rating":"2.43"}],"ARTH 681":[{"InstID":"6042-CAROL-A-HAGAN","revID":"32561","Rating":"3.11"},{"InstID":"6042-CAROL-A-HAGAN","revID":"32561","Rating":"3.11"}],"ARTH 685":[{"InstID":"4746-ANDRE-DOMBROWSKI","revID":"22662","Rating":"3.47"},{"InstID":"4746-ANDRE-DOMBROWSKI","revID":"22662","Rating":"3.47"}],"ARTH 686":[{"InstID":"126-CHRISTINE-POGGI","revID":"31242","Rating":"3.29"},{"InstID":"126-CHRISTINE-POGGI","revID":"31242","Rating":"3.29"}],"ARTH 427":[{"InstID":"1265-ANN-L--KUTTNER","revID":"26990","Rating":"2.67"}],"ARTH 511":[{"InstID":"1267-JULIE-NELSON-DAVIS","revID":"26991","Rating":"3.71"}],"ARTH 581":[{"InstID":"1271-DAVID-B-BROWNLEE","revID":"16984","Rating":"3.43"}],"ARTH 590":[{"InstID":"5288-KAJA-SILVERMAN","revID":"29892","Rating":"3.63"}],"ARTH 141":[{"InstID":"3890-RICHARD-M--LEVENTHAL","revID":"31198","Rating":"3.12"}],"ARTH 205":[{"InstID":"6638-LAURA-E-SURTEES","revID":"31430","Rating":"2.54"}],"ARTH 261":[{"InstID":"1982-LARRY-A--SILVER","revID":"32560","Rating":"3.21"},{"InstID":"1982-LARRY-A--SILVER","revID":"32560","Rating":"3.21"}],"ARTH 500":[{"InstID":"1982-LARRY-A--SILVER","revID":"21298","Rating":"2.88"}],"ARTH 514":[{"InstID":"6624-STEPHEN-H-WHITEMAN","revID":"31248","Rating":"4.00"}],"ARTH 560":[{"InstID":"1332-LILIANE-WEISSBERG","revID":"29040","Rating":"3.00"}],"ARTH 204":[{"InstID":"1273-GEORGE-H--MARCUS","revID":"19780","Rating":"2.14"}],"ARTH 226":[{"InstID":"1265-ANN-L--KUTTNER","revID":"31237","Rating":"3.56"},{"InstID":"1265-ANN-L--KUTTNER","revID":"31237","Rating":"3.56"}],"ARTH 489":[{"InstID":"5726-MIA-L--MASK","revID":"24158","Rating":"3.43"}],"ARTH 543":[{"InstID":"3894-ROBERT-G--OUSTERHOUT","revID":"19796","Rating":"2.83"}],"ARTH 237":[{"InstID":"1332-LILIANE-WEISSBERG","revID":"29033","Rating":"3.09"}],"ARTH 300":[{"InstID":"5288-KAJA-SILVERMAN","revID":"31243","Rating":"3.67"}],"ARTH 416":[{"InstID":"128-RENATA-HOLOD","revID":"21297","Rating":"3.08"}],"ARTH 387":[{"InstID":"5279-DEBORAH-WILLIS","revID":"21223","Rating":"3.22"}],"ARTH 583":[{"InstID":"680-VICTORIA-E-KIRKHAM","revID":"21919","Rating":"2.86"}],"ARTH 121":[{"InstID":"1265-ANN-L--KUTTNER","revID":"22381","Rating":"2.50"},{"InstID":"4968-JUSTIN-THOMAS-MCDANIEL","revID":"22381","Rating":"2.50"}],"ARTH 655":[{"InstID":"5710-CHRISTOPHER-J-NYGREN","revID":"24006","Rating":"3.73"},{"InstID":"5710-CHRISTOPHER-J-NYGREN","revID":"24006","Rating":"3.73"}],"ARTH 683":[{"InstID":"1271-DAVID-B-BROWNLEE","revID":"22661","Rating":"3.38"},{"InstID":"1271-DAVID-B-BROWNLEE","revID":"22661","Rating":"3.38"}],"ARTH 425":[{"InstID":"1265-ANN-L--KUTTNER","revID":"31246","Rating":"3.25"},{"InstID":"4239-LAUREN-M--RISTVET","revID":"31246","Rating":"3.25"}],"ARTH 462":[{"InstID":"1982-LARRY-A--SILVER","revID":"22668","Rating":"3.67"}],"ARTH 386":[{"InstID":"1409-PETER-J--CONN","revID":"23002","Rating":"3.83"}],"ARTH 510":[{"InstID":"4968-JUSTIN-THOMAS-MCDANIEL","revID":"23740","Rating":"3.83"}],"ARTH 247":[{"InstID":"3894-ROBERT-G--OUSTERHOUT","revID":"24005","Rating":"3.08"},{"InstID":"3894-ROBERT-G--OUSTERHOUT","revID":"24005","Rating":"3.08"}],"ARTH 647":[{"InstID":"3894-ROBERT-G--OUSTERHOUT","revID":"24005","Rating":"3.08"},{"InstID":"3894-ROBERT-G--OUSTERHOUT","revID":"24005","Rating":"3.08"}],"ARTH 684":[{"InstID":"4746-ANDRE-DOMBROWSKI","revID":"24008","Rating":"3.70"},{"InstID":"4746-ANDRE-DOMBROWSKI","revID":"24008","Rating":"3.70"}],"ARTH 294":[{"InstID":"5288-KAJA-SILVERMAN","revID":"32564","Rating":"3.69"},{"InstID":"5288-KAJA-SILVERMAN","revID":"32564","Rating":"3.69"}],"ARTH 694":[{"InstID":"5288-KAJA-SILVERMAN","revID":"32564","Rating":"3.69"},{"InstID":"5288-KAJA-SILVERMAN","revID":"32564","Rating":"3.69"}],"ARTH 303":[{"InstID":"1271-DAVID-B-BROWNLEE","revID":"32565","Rating":"2.72"},{"InstID":"137-ANN-BLAIR-BROWNLEE","revID":"32565","Rating":"2.72"}],"ARTH 299":[{"InstID":"5587-LIA-MARKEY","revID":"25263","Rating":"4.00"}],"ARTH 613":[{"InstID":"1267-JULIE-NELSON-DAVIS","revID":"28559","Rating":"3.50"},{"InstID":"1267-JULIE-NELSON-DAVIS","revID":"28559","Rating":"3.50"}],"ARTH 624":[{"InstID":"140-HOLLY-PITTMAN","revID":"28561","Rating":"1.86"},{"InstID":"140-HOLLY-PITTMAN","revID":"28561","Rating":"1.86"}],"ARTH 652":[{"InstID":"1268-CHRISTOPHER-PASTORE","revID":"29878","Rating":"3.67"},{"InstID":"1268-CHRISTOPHER-PASTORE","revID":"29878","Rating":"3.67"}],"ARTH 515":[{"InstID":"144-MICHAEL-W-MEISTER","revID":"25636","Rating":"4.00"}],"ARTH 517":[{"InstID":"128-RENATA-HOLOD","revID":"25637","Rating":"3.38"}],"ARTH 305":[{"InstID":"3241-LEOPOLD-CHARNEY","revID":"25789","Rating":"2.54"}],"ARTH 573":[{"InstID":"2862-GWENDOLYN-D-SHAW","revID":"28569","Rating":"3.22"}],"ARTH 626":[{"InstID":"1265-ANN-L--KUTTNER","revID":"31237","Rating":"3.56"},{"InstID":"1265-ANN-L--KUTTNER","revID":"31237","Rating":"3.56"}],"ARTH 640":[{"InstID":"124-ROBERT-A--MAXWELL","revID":"29877","Rating":"3.00"},{"InstID":"124-ROBERT-A--MAXWELL","revID":"29877","Rating":"3.00"}],"ARTH 661":[{"InstID":"1982-LARRY-A--SILVER","revID":"32560","Rating":"3.21"},{"InstID":"1982-LARRY-A--SILVER","revID":"32560","Rating":"3.21"}],"ARTH 005":[{"InstID":"2862-GWENDOLYN-D-SHAW","revID":"26911","Rating":"2.67"}],"ARTH 315":[{"InstID":"6067-ALEXANDER-RICHARD-GALLOWAY","revID":"27143","Rating":"3.58"}],"ARTH 274":[{"InstID":"5323-KIMBERLY-D--BOWES","revID":"27188","Rating":"3.19"}],"ARTH 537":[{"InstID":"680-VICTORIA-E-KIRKHAM","revID":"27635","Rating":"4.00"}],"ARTH 612":[{"InstID":"144-MICHAEL-W-MEISTER","revID":"28558","Rating":"1.60"},{"InstID":"144-MICHAEL-W-MEISTER","revID":"28558","Rating":"1.60"}],"ARTH 519":[{"InstID":"6230-JULIA-A-PERRATORE","revID":"28567","Rating":"2.50"}],"ARTH 392":[{"InstID":"3224-META-MAZAJ","revID":"28704","Rating":"3.29"}],"ARTH 256":[{"InstID":"5710-CHRISTOPHER-J-NYGREN","revID":"29879","Rating":"3.33"},{"InstID":"5710-CHRISTOPHER-J-NYGREN","revID":"29879","Rating":"3.33"}],"ARTH 656":[{"InstID":"5710-CHRISTOPHER-J-NYGREN","revID":"29879","Rating":"3.33"},{"InstID":"5710-CHRISTOPHER-J-NYGREN","revID":"29879","Rating":"3.33"}],"ARTH 266":[{"InstID":"1982-LARRY-A--SILVER","revID":"29880","Rating":"3.55"},{"InstID":"1982-LARRY-A--SILVER","revID":"29880","Rating":"3.55"}],"ARTH 666":[{"InstID":"1982-LARRY-A--SILVER","revID":"29880","Rating":"3.55"},{"InstID":"1982-LARRY-A--SILVER","revID":"29880","Rating":"3.55"}],"ARTH 675":[{"InstID":"1790-SUZANNE-GLOVER-LINDSAY","revID":"29881","Rating":"2.59"},{"InstID":"1790-SUZANNE-GLOVER-LINDSAY","revID":"29881","Rating":"2.59"}],"ARTH 326":[{"InstID":"1265-ANN-L--KUTTNER","revID":"29885","Rating":"3.00"}],"ARTH 342":[{"InstID":"124-ROBERT-A--MAXWELL","revID":"29886","Rating":"3.33"}],"ARTH 381":[{"InstID":"1271-DAVID-B-BROWNLEE","revID":"29887","Rating":"3.40"}],"ARTH 428":[{"InstID":"1265-ANN-L--KUTTNER","revID":"29888","Rating":"3.50"}],"ARTH 524":[{"InstID":"5097-XIN-WU","revID":"29890","Rating":"2.00"}],"ARTH 233":[{"InstID":"3894-ROBERT-G--OUSTERHOUT","revID":"31238","Rating":"2.60"},{"InstID":"3894-ROBERT-G--OUSTERHOUT","revID":"31238","Rating":"2.60"}],"ARTH 633":[{"InstID":"3894-ROBERT-G--OUSTERHOUT","revID":"31238","Rating":"2.60"},{"InstID":"3894-ROBERT-G--OUSTERHOUT","revID":"31238","Rating":"2.60"}],"ARTH 250":[{"InstID":"6623-DAVID-YOUNG-KIM","revID":"31239","Rating":"3.17"},{"InstID":"6623-DAVID-YOUNG-KIM","revID":"31239","Rating":"3.17"}],"ARTH 650":[{"InstID":"6623-DAVID-YOUNG-KIM","revID":"31239","Rating":"3.17"},{"InstID":"6623-DAVID-YOUNG-KIM","revID":"31239","Rating":"3.17"}],"ARTH 277":[{"InstID":"1271-DAVID-B-BROWNLEE","revID":"31240","Rating":"3.53"},{"InstID":"4746-ANDRE-DOMBROWSKI","revID":"31240","Rating":"3.53"},{"InstID":"1271-DAVID-B-BROWNLEE","revID":"31240","Rating":"3.53"},{"InstID":"4746-ANDRE-DOMBROWSKI","revID":"31240","Rating":"3.53"}],"ARTH 677":[{"InstID":"1271-DAVID-B-BROWNLEE","revID":"31240","Rating":"3.53"},{"InstID":"4746-ANDRE-DOMBROWSKI","revID":"31240","Rating":"3.53"},{"InstID":"1271-DAVID-B-BROWNLEE","revID":"31240","Rating":"3.53"},{"InstID":"4746-ANDRE-DOMBROWSKI","revID":"31240","Rating":"3.53"}],"ARTH 278":[{"InstID":"2862-GWENDOLYN-D-SHAW","revID":"31241","Rating":"3.33"},{"InstID":"2862-GWENDOLYN-D-SHAW","revID":"31241","Rating":"3.33"}],"ARTH 678":[{"InstID":"2862-GWENDOLYN-D-SHAW","revID":"31241","Rating":"3.33"},{"InstID":"2862-GWENDOLYN-D-SHAW","revID":"31241","Rating":"3.33"}],"ARTH 335":[{"InstID":"128-RENATA-HOLOD","revID":"31244","Rating":"4.00"}],"ARTH 389":[{"InstID":"2862-GWENDOLYN-D-SHAW","revID":"31245","Rating":"3.29"}],"ARTH 530":[{"InstID":"127-LOTHAR-HASELBERGER","revID":"31249","Rating":"1.00"}],"ARTH 551":[{"InstID":"1268-CHRISTOPHER-PASTORE","revID":"31250","Rating":"3.60"}],"ARTH 594":[{"InstID":"6625-LEO-BERSANI","revID":"31253","Rating":"3.50"}],"ARTH 393":[{"InstID":"6634-LINDA-R--SIMENSKY","revID":"31386","Rating":"3.79"}],"ARTH 391":[{"InstID":"1403-RITA-BARNARD","revID":"31565","Rating":"3.38"},{"InstID":"2124-TIMOTHY-CORRIGAN","revID":"31565","Rating":"4.00"}],"ARTH 563":[{"InstID":"1480-CATRIONA-MACLEOD","revID":"31747","Rating":"3.33"}],"ARTH 396":[{"InstID":"126-CHRISTINE-POGGI","revID":"32570","Rating":"3.20"}],"ARTH 667":[{"InstID":"1671-GARY-HATFIELD","revID":"32191","Rating":"3.15"}],"ARTH 622":[{"InstID":"140-HOLLY-PITTMAN","revID":"32556","Rating":"2.87"},{"InstID":"140-HOLLY-PITTMAN","revID":"32556","Rating":"2.87"}],"ARTH 629":[{"InstID":"127-LOTHAR-HASELBERGER","revID":"32557","Rating":"3.50"},{"InstID":"127-LOTHAR-HASELBERGER","revID":"32557","Rating":"3.50"}],"ARTH 235":[{"InstID":"128-RENATA-HOLOD","revID":"32558","Rating":"2.46"},{"InstID":"128-RENATA-HOLOD","revID":"32558","Rating":"2.46"}],"ARTH 635":[{"InstID":"128-RENATA-HOLOD","revID":"32558","Rating":"2.46"},{"InstID":"128-RENATA-HOLOD","revID":"32558","Rating":"2.46"}],"ARTH 254":[{"InstID":"6623-DAVID-YOUNG-KIM","revID":"32559","Rating":"2.89"},{"InstID":"6623-DAVID-YOUNG-KIM","revID":"32559","Rating":"2.89"}],"ARTH 654":[{"InstID":"6623-DAVID-YOUNG-KIM","revID":"32559","Rating":"2.89"},{"InstID":"6623-DAVID-YOUNG-KIM","revID":"32559","Rating":"2.89"}],"ARTH 690":[{"InstID":"1267-JULIE-NELSON-DAVIS","revID":"32563","Rating":"3.41"},{"InstID":"1267-JULIE-NELSON-DAVIS","revID":"32563","Rating":"3.41"}],"ARTH 311":[{"InstID":"144-MICHAEL-W-MEISTER","revID":"32566","Rating":"2.33"}],"ARTH 325":[{"InstID":"1265-ANN-L--KUTTNER","revID":"32567","Rating":"3.20"}],"ARTH 328":[{"InstID":"127-LOTHAR-HASELBERGER","revID":"32568","Rating":"2.88"}],"ARTH 351":[{"InstID":"6623-DAVID-YOUNG-KIM","revID":"32569","Rating":"3.80"}],"ARTH 504":[{"InstID":"6635-TERRI-S--FRANCIS","revID":"32719","Rating":"2.86"}],"ARTH 503":[{"InstID":"1480-CATRIONA-MACLEOD","revID":"33092","Rating":"3.40"}]}