{"BIOL 003":[{"InstID":"3229-MICHAEL-PARISI","revID":"19835","Rating":"2.43"}],"BIOL 045":[{"InstID":"178-HELEN-CONRAD-DAVIES","revID":"6240","Rating":"2.91"}],"BIOL 101":[{"InstID":"1283-MEHMET-FEVZI-DALDAL","revID":"31297","Rating":"2.51"},{"InstID":"1296-BRENDA-B-CASPER","revID":"31297","Rating":"2.51"},{"InstID":"6239-KRISTEN-ASHLEY-HIPOLIT","revID":"31297","Rating":"3.20"}],"BIOL 102":[{"InstID":"1286-PAUL-D--SNIEGOWSKI","revID":"32625","Rating":"2.42"},{"InstID":"6051-TIMOTHY-A--LINKSVAYER","revID":"32625","Rating":"2.42"},{"InstID":"6239-KRISTEN-ASHLEY-HIPOLIT","revID":"32625","Rating":"3.39"}],"BIOL 122":[{"InstID":"2881-PAUL-J--DE-WEER","revID":"14163","Rating":"2.67"},{"InstID":"1286-PAUL-D--SNIEGOWSKI","revID":"14163","Rating":"2.86"},{"InstID":"186-DORIS-WAGNER","revID":"14163","Rating":"2.64"}],"BIOL 215":[{"InstID":"190-ARTHUR-E--DUNHAM","revID":"32629","Rating":"1.38"},{"InstID":"2880-XIAOHONG-ZOU-WITMER","revID":"32629","Rating":"2.55"}],"BIOL 221":[{"InstID":"1285-GREGORY-M-GUILD","revID":"32630","Rating":"2.10"},{"InstID":"4147-KIMBERLY-L--GALLAGHER","revID":"32630","Rating":"2.10"},{"InstID":"1285-GREGORY-M-GUILD","revID":"32630","Rating":"2.10"},{"InstID":"4147-KIMBERLY-L--GALLAGHER","revID":"32630","Rating":"2.10"}],"BIOL 229":[{"InstID":"171-NEDRA-LEXOW","revID":"11497","Rating":"3.07"}],"BIOL 230":[{"InstID":"191-PAUL-STUTZ-SCHMIDT","revID":"32631","Rating":"2.52"}],"BIOL 251":[{"InstID":"2877-MICHAEL-KAPLAN","revID":"31305","Rating":"2.68"},{"InstID":"193-EDWIN-G--ABEL","revID":"31305","Rating":"2.68"},{"InstID":"194-MARC-F--SCHMIDT","revID":"31305","Rating":"2.68"}],"BIOL 254":[{"InstID":"198-RICHARD-M-SCHULTZ","revID":"1382","Rating":"3.23"},{"InstID":"1297-ERIC-S--WEINBERG","revID":"1382","Rating":"2.88"}],"BIOL 321":[{"InstID":"196-RUTH-SPORER","revID":"218","Rating":"2.80"}],"BIOL 325":[{"InstID":"197-PETER-S-PETRAITIS","revID":"32635","Rating":"3.06"}],"BIOL 402":[{"InstID":"1802-PHILIP-ARTHUR-REA","revID":"32639","Rating":"3.00"}],"BIOL 404":[{"InstID":"202-MICHAEL-P-CANCRO","revID":"32640","Rating":"2.92"}],"BIOL 409":[{"InstID":"203-INGRID-L-WALDRON","revID":"19852","Rating":"3.38"}],"BIOL 411":[{"InstID":"6051-TIMOTHY-A--LINKSVAYER","revID":"32643","Rating":"2.65"}],"BIOL 432":[{"InstID":"204-DOROTHY-L-CHENEY","revID":"28630","Rating":"3.22"}],"BIOL 483":[{"InstID":"186-DORIS-WAGNER","revID":"31321","Rating":"3.08"}],"BIOL 488":[{"InstID":"2742-MAJA-BUCAN","revID":"32652","Rating":"4.00"},{"InstID":"193-EDWIN-G--ABEL","revID":"32652","Rating":"4.00"},{"InstID":"6845-ROBERT-T--SCHULTZ","revID":"32652","Rating":"4.00"}],"BIOL 516":[{"InstID":"205-THOMAS-L-BOTT","revID":"6264","Rating":"3.50"},{"InstID":"1286-PAUL-D--SNIEGOWSKI","revID":"6264","Rating":"3.25"}],"BIOL 536":[{"InstID":"1805-JUNHYONG-KIM","revID":"25716","Rating":"2.37"}],"BIOL 540":[{"InstID":"208-RICHARD-SCOTT-POETHIG","revID":"29978","Rating":"3.10"}],"BIOL 544":[{"InstID":"206-WARREN-J--EWENS","revID":"6266","Rating":"3.50"}],"BIOL 556":[{"InstID":"197-PETER-S-PETRAITIS","revID":"29979","Rating":"2.80"}],"BIOL 042":[{"InstID":"864-MARY-ANN-LAFFERTY-DELLA-VALLE","revID":"26483","Rating":"2.55"},{"InstID":"5452-KAREN-MOIRA-HOGAN","revID":"26483","Rating":"2.55"},{"InstID":"864-MARY-ANN-LAFFERTY-DELLA-VALLE","revID":"26483","Rating":"2.55"},{"InstID":"5452-KAREN-MOIRA-HOGAN","revID":"26483","Rating":"2.55"}],"BIOL 175":[{"InstID":"864-MARY-ANN-LAFFERTY-DELLA-VALLE","revID":"26483","Rating":"2.55"},{"InstID":"5452-KAREN-MOIRA-HOGAN","revID":"26483","Rating":"2.55"},{"InstID":"864-MARY-ANN-LAFFERTY-DELLA-VALLE","revID":"26483","Rating":"2.55"},{"InstID":"5452-KAREN-MOIRA-HOGAN","revID":"26483","Rating":"2.55"}],"BIOL 010":[{"InstID":"1983-ROBIN-M--SHERWOOD","revID":"6239","Rating":"2.54"}],"BIOL 202":[{"InstID":"4257-JOHN-D--O--WAGNER","revID":"32628","Rating":"2.39"},{"InstID":"199-WEI-GUO","revID":"32628","Rating":"2.39"},{"InstID":"6239-KRISTEN-ASHLEY-HIPOLIT","revID":"32628","Rating":"3.55"}],"BIOL 306":[{"InstID":"1293-DEBORAH-E-WEIL","revID":"32634","Rating":"3.09"}],"BIOL 414":[{"InstID":"197-PETER-S-PETRAITIS","revID":"28628","Rating":"2.93"}],"BIOL 450":[{"InstID":"1803-ANN-F-RHOADS","revID":"15422","Rating":"3.60"},{"InstID":"1804-TIMOTHY-A--BLOCK","revID":"15422","Rating":"3.60"}],"BIOL 465":[{"InstID":"1299-WILLIAM-MCSHEA","revID":"25710","Rating":"2.33"}],"BIOL 480":[{"InstID":"2880-XIAOHONG-ZOU-WITMER","revID":"32648","Rating":"2.67"}],"BIOL 571":[{"InstID":"1802-PHILIP-ARTHUR-REA","revID":"10150","Rating":"3.00"}],"BIOL 008":[{"InstID":"6050-HILLARY-C-M--NELSON","revID":"32622","Rating":"3.46"}],"BIOL 121":[{"InstID":"983-MARK-D-GOULIAN","revID":"32626","Rating":"3.06"},{"InstID":"3905-MICHAEL-A--LAMPSON","revID":"32626","Rating":"3.06"},{"InstID":"3902-DUSTIN-BRISSON","revID":"32626","Rating":"3.06"},{"InstID":"6630-VERONICA-R--MOORMAN","revID":"32626","Rating":"3.06"}],"BIOL 140":[{"InstID":"1287-DANIEL-H-JANZEN","revID":"31300","Rating":"3.00"},{"InstID":"1287-DANIEL-H-JANZEN","revID":"31300","Rating":"3.00"}],"BIOL 440":[{"InstID":"1287-DANIEL-H-JANZEN","revID":"31300","Rating":"3.00"},{"InstID":"1287-DANIEL-H-JANZEN","revID":"31300","Rating":"3.00"}],"BIOL 240":[{"InstID":"2740-JEFFREY-KLEMENS","revID":"31304","Rating":"2.50"},{"InstID":"3232-BRENT-R--HELLIKER","revID":"31304","Rating":"2.50"}],"BIOL 444":[{"InstID":"1296-BRENDA-B-CASPER","revID":"3846","Rating":"2.10"},{"InstID":"190-ARTHUR-E--DUNHAM","revID":"3846","Rating":"1.95"},{"InstID":"1296-BRENDA-B-CASPER","revID":"3846","Rating":"2.10"},{"InstID":"190-ARTHUR-E--DUNHAM","revID":"3846","Rating":"1.95"}],"BIOL 330":[{"InstID":"190-ARTHUR-E--DUNHAM","revID":"32636","Rating":"2.45"}],"BIOL 406":[{"InstID":"184-DAVID-S--ROOS","revID":"32641","Rating":"2.67"}],"BIOL 407":[{"InstID":"1295-BRIAN-D--KEITH","revID":"32642","Rating":"3.75"},{"InstID":"4260-SHUJUAN-XIA","revID":"32642","Rating":"3.18"}],"BIOL 412":[{"InstID":"1296-BRENDA-B-CASPER","revID":"8609","Rating":"2.44"},{"InstID":"190-ARTHUR-E--DUNHAM","revID":"8609","Rating":"2.33"}],"BIOL 421":[{"InstID":"1297-ERIC-S--WEINBERG","revID":"31313","Rating":"2.74"}],"BIOL 446":[{"InstID":"4757-JOSHUA-B--PLOTKIN","revID":"31316","Rating":"2.83"}],"BIOL 451":[{"InstID":"194-MARC-F--SCHMIDT","revID":"32647","Rating":"3.31"},{"InstID":"4262-JAVIER-F--MEDINA","revID":"32647","Rating":"3.31"}],"BIOL 475":[{"InstID":"1283-MEHMET-FEVZI-DALDAL","revID":"22734","Rating":"2.59"},{"InstID":"865-MECHTHILD-POHLSCHRODER","revID":"22734","Rating":"2.59"}],"BIOL 514":[{"InstID":"205-THOMAS-L-BOTT","revID":"2705","Rating":"2.75"}],"BIOL 523":[{"InstID":"1299-WILLIAM-MCSHEA","revID":"2706","Rating":"2.33"}],"BIOL 526":[{"InstID":"4147-KIMBERLY-L--GALLAGHER","revID":"29977","Rating":"2.72"}],"BIOL 537":[{"InstID":"247-SAMPATH-K--KANNAN","revID":"11513","Rating":"3.45"},{"InstID":"206-WARREN-J--EWENS","revID":"11513","Rating":"3.45"}],"BIOL 539":[{"InstID":"1300-MING-H--YUK","revID":"3864","Rating":"2.33"}],"BIOL 219":[{"InstID":"2877-MICHAEL-KAPLAN","revID":"19822","Rating":"3.36"}],"BIOL 431":[{"InstID":"5295-BRIAN-D--GREGORY","revID":"32645","Rating":"3.40"}],"BIOL 231":[{"InstID":"204-DOROTHY-L-CHENEY","revID":"32274","Rating":"2.63"},{"InstID":"1693-ROBERT-M-SEYFARTH","revID":"32274","Rating":"2.63"}],"BIOL 007":[{"InstID":"3230-PHILIP-L-COHEN","revID":"11485","Rating":"2.79"}],"BIOL 400":[{"InstID":"1803-ANN-F-RHOADS","revID":"3848","Rating":"3.33"},{"InstID":"1804-TIMOTHY-A--BLOCK","revID":"3848","Rating":"3.33"}],"BIOL 410":[{"InstID":"1286-PAUL-D--SNIEGOWSKI","revID":"31312","Rating":"3.45"},{"InstID":"4757-JOSHUA-B--PLOTKIN","revID":"31312","Rating":"3.45"}],"BIOL 528":[{"InstID":"1297-ERIC-S--WEINBERG","revID":"12956","Rating":"3.00"},{"InstID":"1297-ERIC-S--WEINBERG","revID":"12956","Rating":"3.00"}],"BIOL 438":[{"InstID":"1289-LAWRENCE-C--ROME","revID":"32646","Rating":"3.08"}],"BIOL 442":[{"InstID":"193-EDWIN-G--ABEL","revID":"31315","Rating":"3.11"},{"InstID":"4254-ISABEL-MUZZIO","revID":"31315","Rating":"3.11"}],"BIOL 004":[{"InstID":"2410-MICHAEL-PAZIANAS","revID":"5041","Rating":"3.17"}],"BIOL 005":[{"InstID":"2411-GLEN-N-GAULTON","revID":"24056","Rating":"3.31"}],"BIOL 011":[{"InstID":"3902-DUSTIN-BRISSON","revID":"31295","Rating":"2.50"}],"BIOL 527":[{"InstID":"1285-GREGORY-M-GUILD","revID":"32630","Rating":"2.10"},{"InstID":"4147-KIMBERLY-L--GALLAGHER","revID":"32630","Rating":"2.10"},{"InstID":"1285-GREGORY-M-GUILD","revID":"32630","Rating":"2.10"},{"InstID":"4147-KIMBERLY-L--GALLAGHER","revID":"32630","Rating":"2.10"}],"BIOL 419":[{"InstID":"208-RICHARD-SCOTT-POETHIG","revID":"5061","Rating":"2.40"},{"InstID":"191-PAUL-STUTZ-SCHMIDT","revID":"5061","Rating":"2.23"}],"BIOL 436":[{"InstID":"2068-DEJIAN-REN","revID":"28631","Rating":"2.94"}],"BIOL 130":[{"InstID":"183-MICHAEL-J-BALSAI","revID":"6244","Rating":"2.10"}],"BIOL 150":[{"InstID":"203-INGRID-L-WALDRON","revID":"14164","Rating":"2.78"},{"InstID":"2741-JENNIFER-HELEN-DOHERTY","revID":"14164","Rating":"2.83"}],"BIOL 354":[{"InstID":"4257-JOHN-D--O--WAGNER","revID":"32637","Rating":"2.15"}],"BIOL 415":[{"InstID":"6053-DAVID-BERTRAM-ARSCOTT","revID":"32644","Rating":"2.54"}],"BIOL 455":[{"InstID":"208-RICHARD-SCOTT-POETHIG","revID":"6259","Rating":"3.33"}],"BIOL 009":[{"InstID":"2879-JOAN-P-GIRESI","revID":"14160","Rating":"2.08"},{"InstID":"2879-JOAN-P-GIRESI","revID":"14160","Rating":"1.80"}],"BIOL 484":[{"InstID":"2416-TATYANA-M--SVITKINA","revID":"31322","Rating":"3.75"}],"BIOL 014":[{"InstID":"1286-PAUL-D--SNIEGOWSKI","revID":"28611","Rating":"3.40"}],"BIOL 423":[{"InstID":"1296-BRENDA-B-CASPER","revID":"27059","Rating":"3.47"}],"BIOL 012":[{"InstID":"3903-DAVID-L-GASSER","revID":"18344","Rating":"2.00"}],"BIOL 275":[{"InstID":"2415-EBY-A--BASSIRI","revID":"32632","Rating":"2.64"}],"BIOL 575":[{"InstID":"865-MECHTHILD-POHLSCHRODER","revID":"32638","Rating":"2.83"},{"InstID":"865-MECHTHILD-POHLSCHRODER","revID":"32638","Rating":"2.83"}],"BIOL 017":[{"InstID":"208-RICHARD-SCOTT-POETHIG","revID":"32624","Rating":"2.92"}],"BIOL 124":[{"InstID":"1290-LINDA-J--ROBINSON","revID":"32627","Rating":"2.37"}],"BIOL 422":[{"InstID":"4261-SARAH-A--TISHKOFF","revID":"29971","Rating":"2.36"}],"BIOL 445":[{"InstID":"6465-LILLIAN-W--CHIANG","revID":"29973","Rating":"3.13"},{"InstID":"6466-DANIEL-LAVERY","revID":"29973","Rating":"3.13"}],"BIOL 482":[{"InstID":"4147-KIMBERLY-L--GALLAGHER","revID":"32649","Rating":"3.19"}],"BIOL 486":[{"InstID":"3905-MICHAEL-A--LAMPSON","revID":"32651","Rating":"3.50"}],"BIOL 448":[{"InstID":"4758-DAVID-R--MANNING","revID":"31317","Rating":"3.47"}],"BIOL 109":[{"InstID":"4254-ISABEL-MUZZIO","revID":"32610","Rating":"3.06"},{"InstID":"2876-JUDITH-MCLEAN","revID":"32610","Rating":"2.90"}],"BIOL 506":[{"InstID":"204-DOROTHY-L-CHENEY","revID":"18369","Rating":"4.00"}],"BIOL 255":[{"InstID":"208-RICHARD-SCOTT-POETHIG","revID":"19844","Rating":"3.00"},{"InstID":"186-DORIS-WAGNER","revID":"19844","Rating":"3.00"}],"BIOL 015":[{"InstID":"1297-ERIC-S--WEINBERG","revID":"32623","Rating":"2.89"}],"BIOL 485":[{"InstID":"5295-BRIAN-D--GREGORY","revID":"32650","Rating":"3.29"}],"BIOL 019":[{"InstID":"5590-DAVID-ALAN-HEWITT","revID":"31296","Rating":"3.67"}],"BIOL 151":[{"InstID":"5591-DANIEL-S-KESSLER","revID":"22718","Rating":"3.80"},{"InstID":"5592-JAMIE-R--SHUDA","revID":"22718","Rating":"3.80"}],"BIOL 530":[{"InstID":"1805-JUNHYONG-KIM","revID":"22738","Rating":"3.25"}],"BIOL 477":[{"InstID":"5714-STEPHEN-A-ROTH","revID":"31318","Rating":"3.75"}],"BIOL 522":[{"InstID":"4261-SARAH-A--TISHKOFF","revID":"27068","Rating":"2.92"}],"BIOL 437":[{"InstID":"1805-JUNHYONG-KIM","revID":"31314","Rating":"2.67"}],"BIOL 474":[{"InstID":"6054-ILAN-ROSENSHEIN","revID":"27064","Rating":"1.79"}],"BIOL 375":[{"InstID":"865-MECHTHILD-POHLSCHRODER","revID":"32638","Rating":"2.83"},{"InstID":"865-MECHTHILD-POHLSCHRODER","revID":"32638","Rating":"2.83"}],"BIOL 304":[{"InstID":"5712-CARSTEN-SANDERS","revID":"32633","Rating":"2.91"}],"BIOL 493":[{"InstID":"5591-DANIEL-S-KESSLER","revID":"32653","Rating":"3.88"},{"InstID":"6846-SHELLEY-L--BERGER","revID":"32653","Rating":"3.88"},{"InstID":"6847-MORGAN-A-SAMMONS","revID":"32653","Rating":"3.88"}]}