{"ENGR 105":[{"InstID":"6655-GRAHAM-WABISZEWSKI","revID":"32909","Rating":"2.92"},{"InstID":"4750-MICHAEL-RIZK","revID":"32909","Rating":"2.49"}],"ENGR 250":[{"InstID":"5231-ANDREW-JACKSON","revID":"32910","Rating":"2.73"}],"ENGR 299":[{"InstID":"350-JAN-DER-SPIEGEL","revID":"31575","Rating":"2.00"},{"InstID":"1795-BETH-A--WINKELSTEIN","revID":"31575","Rating":"2.54"}],"ENGR 504":[{"InstID":"774-MICHAEL-A--CARCHIDI","revID":"31576","Rating":"3.20"}],"ENGR 566":[{"InstID":"1795-BETH-A--WINKELSTEIN","revID":"32911","Rating":"3.43"},{"InstID":"5386-SARAH-E--ROTTENBERG","revID":"32911","Rating":"3.43"}]}