{"LING 001":{"courseListName":"LING 001","courseTitle":"Introduction to Linguistics","PCR":2.57},"LING 057":{"courseListName":"LING 057","courseTitle":"The Evolution of Language","PCR":1.44},"LING 071":{"courseListName":"LING 071","courseTitle":"American Sign Language I","PCR":3.61},"LING 072":{"courseListName":"LING 072","courseTitle":"American Sign Language II","PCR":2.85},"LING 073":{"courseListName":"LING 073","courseTitle":"American Sign Language III","PCR":2.69},"LING 074":{"courseListName":"LING 074","courseTitle":"American Sign Language IV","PCR":2.98},"LING 077":{"courseListName":"LING 077","courseTitle":"ASL/Deaf Studies - ABCS","PCR":3.25},"LING 078":{"courseListName":"LING 078","courseTitle":"Deaf Culture","PCR":4},"LING 082":{"courseListName":"LING 082","courseTitle":"Beginning Irish Gaelic II","PCR":3.5},"LING 084":{"courseListName":"LING 084","courseTitle":"Intermediate Irish Gaelic II","PCR":4},"LING 086":{"courseListName":"LING 086","courseTitle":"Advanced Irish Gaelic II","PCR":3.5},"LING 102":{"courseListName":"LING 102","courseTitle":"Introduction to Sociolinguistics","PCR":2.22},"LING 229":{"courseListName":"LING 229","courseTitle":"Fr Dans Monde/Fr in Wrld"},"LING 230":{"courseListName":"LING 230","courseTitle":"Sound Structure of Language","PCR":3.19},"LING 247":{"courseListName":"LING 247","courseTitle":"Structure of American Sign Language","PCR":3.8},"LING 302":{"courseListName":"LING 302","courseTitle":"Linguistic Field Methods","PCR":2.17},"LING 405":{"courseListName":"LING 405","courseTitle":"Morphology Theory II","PCR":4},"LING 502":{"courseListName":"LING 502","courseTitle":"Linguistic Field Methods","PCR":2.17},"LING 503":{"courseListName":"LING 503","courseTitle":"Sound Structure of Language","PCR":3.19},"LING 521":{"courseListName":"LING 521","courseTitle":"Introduction to Phonetics II","PCR":1.67},"LING 531":{"courseListName":"LING 531","courseTitle":"Phonology II","PCR":3.2},"LING 551":{"courseListName":"LING 551","courseTitle":"Syntax II","PCR":3},"LING 570":{"courseListName":"LING 570","courseTitle":"Developmental Psycholinguistics","PCR":3},"LING 581":{"courseListName":"LING 581","courseTitle":"Semantics II","PCR":3.33},"LING 603":{"courseListName":"LING 603","courseTitle":"Topics in Phonology"},"LING 608":{"courseListName":"LING 608","courseTitle":"Topics in Semantics and Pragmatics"},"LING 630":{"courseListName":"LING 630","courseTitle":"Seminar in Morphology"},"LING 650":{"courseListName":"LING 650","courseTitle":"Topics in Natural-Language Syntax"},"LING 670":{"courseListName":"LING 670","courseTitle":"Topics in the Cultural Evolution of Language"}}